setup.py
webassets_rollup/__init__.py
webassets_rollup.egg-info/PKG-INFO
webassets_rollup.egg-info/SOURCES.txt
webassets_rollup.egg-info/dependency_links.txt
webassets_rollup.egg-info/requires.txt
webassets_rollup.egg-info/top_level.txt
webassets_rollup/tests/__init__.py
webassets_rollup/tests/test_rollup.py