Metadata-Version: 1.1
Name: webassets-rollup
Version: 1.0.0
Summary: Rollup filter for webassets
Home-page: https://github.com/rclmenezes/webassets-rollup
Author: Rodrigo Menezes
Author-email: UNKNOWN
License: MIT
Keywords: rollup,webassets,django assets
Platform: UNKNOWN
Classifier: Development Status :: 5 - Production/Stable
Classifier: Intended Audience :: Developers
Classifier: License :: OSI Approved :: MIT License
Classifier: Programming Language :: Python :: 2.7
Classifier: Programming Language :: Python :: 3.3
Classifier: Programming Language :: Python :: 3.4
Classifier: Programming Language :: Python :: 3.5
